pavaule_de_toolkit/__init__.py
pavaule_de_toolkit/main.py
pavaule_de_toolkit/vm.py
pavaule_de_toolkit-0.1.0.dist-info/METADATA
pavaule_de_toolkit-0.1.0.dist-info/WHEEL
pavaule_de_toolkit-0.1.0.dist-info/entry_points.txt
pavaule_de_toolkit-0.1.0.dist-info/RECORD
